br4wlst4rs/__init__.py
br4wlst4rs/core.py
br4wlst4rs/requests.py
br4wlst4rs/config/config.json
br4wlst4rs/js/base_address.js
br4wlst4rs/js/rec_post.js
br4wlst4rs-0.2.dist-info/METADATA
br4wlst4rs-0.2.dist-info/WHEEL
br4wlst4rs-0.2.dist-info/top_level.txt
br4wlst4rs-0.2.dist-info/RECORD
